.travis.yml
MANIFEST.in
README.rst
manage.py
runtests.py
setup.py
tox.ini
django_otp_sms.egg-info/PKG-INFO
django_otp_sms.egg-info/SOURCES.txt
django_otp_sms.egg-info/dependency_links.txt
django_otp_sms.egg-info/requires.txt
django_otp_sms.egg-info/top_level.txt
otp_sms/__init__.py
otp_sms/backends.py
otp_sms/conf.py
otp_sms/forms.py
otp_sms/models.py
otp_sms/signals.py
otp_sms/tests.py
otp_sms/views.py
otp_sms/adapters/__init__.py
otp_sms/adapters/base.py
otp_sms/adapters/prostor.py
otp_sms/adapters/smsru.py
otp_sms/locale/ru/LC_MESSAGES/django.mo
otp_sms/locale/ru/LC_MESSAGES/django.po
otp_sms/migrations/0001_initial.py
otp_sms/migrations/0002_auto_20161114_1650.py
otp_sms/migrations/0003_auto_20220120_0922.py
otp_sms/migrations/__init__.py
tests/__init__.py
tests/test_settings.py
tests/tests.py
tests/urls.py